rosa/__init__.py
rosa/cli.py
rosa/tests/__init__.py
rosa/tests/conftest.py
rosa/tests/const.py
rosa/tests/test_parse_command.py
rosa_python_client-1.0.28.dist-info/METADATA
rosa_python_client-1.0.28.dist-info/WHEEL
rosa_python_client-1.0.28.dist-info/RECORD
