Metadata-Version: 2.1
Name: rosa-python-client
Version: 1.0.28
Summary: Wrapper for rosa cli
Author: Meni Yakove
Author-email: myakove@gmail.com
Requires-Python: >=3.8,<4.0
Classifier: Programming Language :: Python :: 3
Classifier: Programming Language :: Python :: 3.8
Classifier: Programming Language :: Python :: 3.9
Classifier: Programming Language :: Python :: 3.10
Classifier: Programming Language :: Python :: 3.11
Requires-Dist: python-benedict (>=0.32.0,<0.33.0)
Requires-Dist: python-simple-logger (>=1.0.5,<2.0.0)
Requires-Dist: redhat-qe-cloud-tools (>=1.0.6,<2.0.0)
